{
    "returnValue":true,
    "results":[
        {
            "settings":{
                "mhegGuide":"off",
                "ohtv":"on",
                "dataService":"mheg",
                "hbbTV":"off",
                "hybridCast":"off",
                "interactivity":"off",
                "mhpAutoStart":"off"
            },
            "category":"option",
            "method":"getSystemSettings",
            "returnValue":true
        },
        {
            "settings":{
                "analogSystemColor":"multi",
                "autoscanChannelGroup":"primary_channel",
                "channelsInHome":"on"
            },
            "category":"channel",
            "method":"getSystemSettings",
            "returnValue":true
        },
        {
            "settings":{
                "camPinCode":"N.A"
            },
            "category":"lock",
            "method":"getSystemSettings",
            "returnValue":true
        },
        {
            "returnValue":true,
            "results":[
                {
                    "category":"option",
                    "vtype":"ArrayExt",
                    "dbtype":"G",
                    "valueCheck":false,
                    "key":"dataService",
                    "hasCountryVar":true,
                    "volatile":false,
                    "dimension":[

                    ],
                    "ui":{
                        "active":false,
                        "visible":false,
                        "widget":"None",
                        "displayName":"dataService"
                    },
                    "values":{
                        "arrayExt":[
                            {
                                "active":true,
                                "visible":true,
                                "value":"mheg"
                            },
                            {
                                "active":true,
                                "visible":true,
                                "value":"ttx"
                            }
                        ]
                    }
                },
                {
                    "category":"option",
                    "ui":{
                        "active":false,
                        "visible":false,
                        "widget":"None",
                        "displayName":"hbbTV"
                    },
                    "vtype":"ArrayExt",
                    "dbtype":"G",
                    "valueCheck":true,
                    "values":{
                        "arrayExt":[
                            {
                                "active":true,
                                "visible":true,
                                "value":"on"
                            },
                            {
                                "active":true,
                                "visible":true,
                                "value":"off"
                            }
                        ]
                    },
                    "key":"hbbTV",
                    "hasCountryVar":true,
                    "volatile":false,
                    "dimension":[

                    ]
                },
                {
                    "category":"option",
                    "ui":{
                        "active":false,
                        "visible":false,
                        "widget":"None",
                        "displayName":"hybridCast"
                    },
                    "vtype":"ArrayExt",
                    "dbtype":"G",
                    "valueCheck":true,
                    "values":{
                        "arrayExt":[
                            {
                                "active":true,
                                "visible":true,
                                "value":"on"
                            },
                            {
                                "active":true,
                                "visible":true,
                                "value":"off"
                            }
                        ]
                    },
                    "key":"hybridCast",
                    "hasCountryVar":true,
                    "volatile":false,
                    "dimension":[

                    ]
                },
                {
                    "category":"option",
                    "vtype":"ArrayExt",
                    "dbtype":"G",
                    "valueCheck":false,
                    "key":"interactivity",
                    "hasCountryVar":true,
                    "volatile":false,
                    "dimension":[

                    ],
                    "ui":{
                        "active":false,
                        "visible":false,
                        "widget":"None",
                        "displayName":"interactivity"
                    },
                    "values":{
                        "arrayExt":[
                            {
                                "active":true,
                                "visible":true,
                                "value":"on"
                            },
                            {
                                "active":true,
                                "visible":true,
                                "value":"off"
                            }
                        ]
                    }
                },
                {
                    "category":"option",
                    "vtype":"ArrayExt",
                    "dbtype":"G",
                    "valueCheck":false,
                    "key":"mhegGuide",
                    "volatile":false,
                    "dimension":[

                    ],
                    "ui":{
                        "active":false,
                        "visible":false,
                        "widget":"None",
                        "displayName":"mhegGuide"
                    },
                    "values":{
                        "arrayExt":[
                            {
                                "active":true,
                                "visible":true,
                                "value":"on"
                            },
                            {
                                "active":true,
                                "visible":true,
                                "value":"off"
                            }
                        ]
                    }
                },
                {
                    "category":"option",
                    "vtype":"ArrayExt",
                    "dbtype":"G",
                    "valueCheck":false,
                    "key":"mhpAutoStart",
                    "hasCountryVar":true,
                    "volatile":false,
                    "dimension":[

                    ],
                    "ui":{
                        "active":false,
                        "visible":false,
                        "widget":"None",
                        "displayName":"mhpAutoStart"
                    },
                    "values":{
                        "arrayExt":[
                            {
                                "active":true,
                                "visible":true,
                                "value":"on"
                            },
                            {
                                "active":true,
                                "visible":true,
                                "value":"off"
                            }
                        ]
                    }
                },
                {
                    "category":"option",
                    "ui":{
                        "active":true,
                        "visible":true,
                        "widget":"N",
                        "displayName":"ohtv"
                    },
                    "vtype":"ArrayExt",
                    "dbtype":"G",
                    "valueCheck":false,
                    "values":{
                        "arrayExt":[
                            {
                                "active":true,
                                "visible":true,
                                "value":"on"
                            },
                            {
                                "active":true,
                                "visible":true,
                                "value":"off"
                            }
                        ]
                    },
                    "key":"ohtv",
                    "volatile":false,
                    "dimension":[

                    ]
                }
            ],
            "method":"getSystemSettingDesc"
        },
        {
            "returnValue":true,
            "results":[
                {
                    "category":"channel",
                    "ui":{
                        "active":true,
                        "visible":true,
                        "widget":"None",
                        "displayName":"analogSystemColor"
                    },
                    "vtype":"ArrayExt",
                    "dbtype":"G",
                    "valueCheck":true,
                    "values":{
                        "arrayExt":[
                            {
                                "active":true,
                                "visible":true,
                                "value":"multi"
                            },
                            {
                                "active":true,
                                "visible":true,
                                "value":"pal-m"
                            },
                            {
                                "active":true,
                                "visible":true,
                                "value":"pal-n"
                            },
                            {
                                "active":true,
                                "visible":true,
                                "value":"ntsc"
                            }
                        ]
                    },
                    "key":"analogSystemColor",
                    "volatile":false,
                    "dimension":[

                    ]
                },
                {
                    "category":"channel",
                    "ui":{
                        "active":true,
                        "visible":true,
                        "widget":"None",
                        "displayName":"autoscanChannelGroup"
                    },
                    "vtype":"ArrayExt",
                    "dbtype":"G",
                    "valueCheck":true,
                    "values":{
                        "arrayExt":[
                            {
                                "active":true,
                                "visible":true,
                                "value":"primary_channel"
                            },
                            {
                                "active":true,
                                "visible":true,
                                "value":"all_channel"
                            }
                        ]
                    },
                    "key":"autoscanChannelGroup",
                    "hasCountryVar":true,
                    "volatile":false,
                    "dimension":[

                    ]
                },
                {
                    "category":"channel",
                    "ui":{
                        "active":true,
                        "visible":true,
                        "widget":"None",
                        "displayName":"channelsInHome"
                    },
                    "vtype":"ArrayExt",
                    "dbtype":"G",
                    "valueCheck":true,
                    "values":{
                        "arrayExt":[
                            {
                                "active":true,
                                "visible":true,
                                "value":"on"
                            },
                            {
                                "active":true,
                                "visible":true,
                                "value":"off"
                            }
                        ]
                    },
                    "key":"channelsInHome",
                    "volatile":false,
                    "dimension":[

                    ]
                }
            ],
            "method":"getSystemSettingDesc"
        }
    ]
}
